tacc_inf/README.md
tacc_inf/__init__.py
tacc_inf/cli/__init__.py
tacc_inf/cli/_cli.py
tacc_inf/cli/_utils.py
tacc_inf/find_port.sh
tacc_inf/launch_server.sh
tacc_inf/models/README.md
tacc_inf/models/models.csv
tacc_inf/multinode_vllm.slurm
tacc_inf/vllm.slurm
tacc_inf-0.2.2.dist-info/LICENSE
tacc_inf-0.2.2.dist-info/METADATA
tacc_inf-0.2.2.dist-info/WHEEL
tacc_inf-0.2.2.dist-info/entry_points.txt
tacc_inf-0.2.2.dist-info/RECORD
