Metadata-Version: 2.1
Name: tacc-inf
Version: 0.2.2
Summary: Efficient LLM inference on Slurm clusters using vLLM (for TACC).
License: MIT
Author: Atharva Sehgal
Author-email: atharvas@utexas.edu
Requires-Python: >=3.10,<4.0
Classifier: License :: OSI Approved :: MIT License
Classifier: Programming Language :: Python :: 3
Classifier: Programming Language :: Python :: 3.10
Classifier: Programming Language :: Python :: 3.11
Classifier: Programming Language :: Python :: 3.12
Classifier: Programming Language :: Python :: 3.13
Provides-Extra: dev
Requires-Dist: click (>=8.1.0,<9.0.0)
Requires-Dist: cupy-cuda12x (==12.1.0) ; extra == "dev"
Requires-Dist: pandas (>=2.2.2,<3.0.0)
Requires-Dist: ray (>=2.9.3,<3.0.0) ; extra == "dev"
Requires-Dist: requests (>=2.31.0,<3.0.0)
Requires-Dist: rich (>=13.7.0,<14.0.0)
Requires-Dist: starlette (>=0.40.0)
Requires-Dist: vllm (>=0.5.0,<0.6.0) ; extra == "dev"
Requires-Dist: vllm-nccl-cu12 (>=2.18,<2.19) ; extra == "dev"
